rizemind/__init__.py
rizemind/constants.py
rizemind/authentication/__init__.py
rizemind/authentication/authenticated_client_manager.py
rizemind/authentication/authenticated_client_properties.py
rizemind/authentication/authentication_mod.py
rizemind/authentication/can_train_criterion.py
rizemind/authentication/config.py
rizemind/authentication/eth_account_strategy.py
rizemind/authentication/train_auth.py
rizemind/authentication/typing.py
rizemind/authentication/notary/model/config.py
rizemind/authentication/notary/model/mod.py
rizemind/authentication/notary/model/model_signature.py
rizemind/authentication/signatures/auth.py
rizemind/authentication/signatures/eip712.py
rizemind/authentication/signatures/signature.py
rizemind/cli/__init__.py
rizemind/cli/account/__init__.py
rizemind/cli/account/loader.py
rizemind/cli/account/options.py
rizemind/cli/swarm/__init__.py
rizemind/configuration/__init__.py
rizemind/configuration/base_config.py
rizemind/configuration/toml_config.py
rizemind/configuration/transform.py
rizemind/configuration/validators/eth_address.py
rizemind/contracts/__init__.py
rizemind/contracts/abi.py
rizemind/contracts/abi_helper.py
rizemind/contracts/base_contract.py
rizemind/contracts/deployment.py
rizemind/contracts/has_account.py
rizemind/contracts/local_deployment.py
rizemind/contracts/access_control/fl_access_control/FlAccessControl.py
rizemind/contracts/access_control/fl_access_control/abi.json
rizemind/contracts/erc/erc5267/erc5267.abi.json
rizemind/contracts/erc/erc5267/erc5267.py
rizemind/contracts/erc/erc5267/typings.py
rizemind/contracts/sampling/always_sampled.py
rizemind/contracts/sampling/selector_factory.py
rizemind/contracts/sampling/selector_factory_abi.json
rizemind/contracts/sampling/random_sampling/__init__.py
rizemind/contracts/sampling/random_sampling/abi.json
rizemind/contracts/swarm/constants.py
rizemind/contracts/swarm/contributions/trainer_contributed_event.abi.json
rizemind/contracts/swarm/contributions/trainers_contributed.py
rizemind-0.0.3.dist-info/METADATA
rizemind-0.0.3.dist-info/WHEEL
rizemind-0.0.3.dist-info/entry_points.txt
rizemind-0.0.3.dist-info/RECORD
