Metadata-Version: 2.4
Name: rizemind
Version: 0.0.3
Summary: RIZEMIND: building decentralized collective intelligence
Author-email: T-RIZE Labs <michael.duchesne@t-rize.io>
License-Expression: Apache-2.0
Requires-Python: >=3.12
Requires-Dist: brotli>=1.1.0
Requires-Dist: dotenv>=0.9.9
Requires-Dist: eth-account>=0.13.6
Requires-Dist: eth-tester>=0.13.0b1
Requires-Dist: flwr[simulation]>=1.17.0
Requires-Dist: mlflow>=3.3.2
Requires-Dist: mnemonic>=0.21
Requires-Dist: numpy>=1.26.4
Requires-Dist: pydantic>=2.11.3
Requires-Dist: tomli>=2.2.1
Requires-Dist: typer>=0.12.5
Requires-Dist: web3>=7.10.0
Requires-Dist: zstandard>=0.23.0
